fastoo/__init__.py
fastoo/app.py
fastoo/cli.py
fastoo/config.py
fastoo/init.py
fastoo/api/__init__.py
fastoo/api/cli.py
fastoo/api/file.py
fastoo/api/module.py
fastoo/api/templates.py
fastoo/api/validators.py
fastoo/api/verify.py
fastoo/modules/www/business.py
fastoo/modules/www/forms.py
fastoo/modules/www/models.py
fastoo/modules/www/view.py
Fastoo-0.1.4.dist-info/LICENSE
Fastoo-0.1.4.dist-info/METADATA
Fastoo-0.1.4.dist-info/WHEEL
Fastoo-0.1.4.dist-info/entry_points.txt
Fastoo-0.1.4.dist-info/top_level.txt
Fastoo-0.1.4.dist-info/RECORD
