Metadata-Version: 2.1
Name: Fastoo
Version: 0.1.4
Summary: A super-charged FastAPI framework for even faster delivery
Maintainer-email: Abdur-Rahmaan Janhangeer <arj.python@gmail.com>
Project-URL: Source Code, https://github.com/Abdur-rahmaanJ/fastoo
Project-URL: Issue Tracker, https://github.com/Abdur-rahmaanJ/fastoo/issues/
Classifier: Environment :: Web Environment
Classifier: Intended Audience :: Developers
Classifier: Operating System :: OS Independent
Classifier: Programming Language :: Python
Classifier: Topic :: Software Development :: Libraries :: Application Frameworks
Requires-Python: >=3.8
License-File: LICENSE
Requires-Dist: fastapi
Requires-Dist: uvicorn
Requires-Dist: pydantic-settings
Requires-Dist: toml
Requires-Dist: pyyaml
Requires-Dist: starlette-wtf
Requires-Dist: importlib-metadata >=3.6.0 ; python_version < "3.10"
